{
  "posts": [
    {
      "data": [
        {
          "id": "254deeba-0e38-41ae-8907-9d5d6fbd4dba",
          "note": "ccc",
          "date": "2022-05-30",
          "time": "01:59"
        },
        {
          "id": "44547af4-8f9e-4709-8eb4-0b85f9d93b5e",
          "note": "bbb",
          "date": "2022-05-30",
          "time": "01:59"
        },
        {
          "id": "50e6fb95-abb1-4883-ac67-ac401254f496",
          "note": "aaa",
          "date": "2022-05-30",
          "time": "01:59"
        }
      ],
      "id": "1"
    }
  ]
}